quantalogic_flow/__init__.py
quantalogic_flow/flow/__init__.py
quantalogic_flow/flow/core/__init__.py
quantalogic_flow/flow/core/engine.py
quantalogic_flow/flow/core/events.py
quantalogic_flow/flow/core/sub_workflow.py
quantalogic_flow/flow/core/workflow.py
quantalogic_flow/flow/examples.py
quantalogic_flow/flow/flow.py
quantalogic_flow/flow/flow_extractor.py
quantalogic_flow/flow/flow_generator.py
quantalogic_flow/flow/flow_manager.py
quantalogic_flow/flow/flow_manager_schema.py
quantalogic_flow/flow/flow_mermaid.py
quantalogic_flow/flow/flow_modular.py
quantalogic_flow/flow/flow_validator.py
quantalogic_flow/flow/nodes/__init__.py
quantalogic_flow/flow/nodes/base.py
quantalogic_flow/flow/nodes/decorators.py
quantalogic_flow/flow/nodes/template_nodes.py
quantalogic_flow/flow/template/__init__.py
quantalogic_flow/flow/template/engine.py
quantalogic_flow/flow/template/utils.py
quantalogic_flow/flow/templates/prompt_check_inventory.j2
quantalogic_flow/flow/templates/system_check_inventory.j2
quantalogic_flow-0.7.1.dist-info/METADATA
quantalogic_flow-0.7.1.dist-info/WHEEL
quantalogic_flow-0.7.1.dist-info/RECORD
