Metadata-Version: 2.3
Name: quantalogic-flow
Version: 0.7.1
Summary: Quantalogic Flow
License: MIT
Author: QuantaLogic Team
Author-email: raphael.mansuy@quantalogic.app
Requires-Python: >=3.10,<4.0
Classifier: License :: OSI Approved :: MIT License
Classifier: Programming Language :: Python :: 3
Classifier: Programming Language :: Python :: 3.10
Classifier: Programming Language :: Python :: 3.11
Classifier: Programming Language :: Python :: 3.12
Classifier: Programming Language :: Python :: 3.13
Requires-Dist: google-auth (>=2.40.3,<3.0.0)
Requires-Dist: instructor (>=1.11.2,<2.0.0)
Requires-Dist: jinja2 (>=3.1.5,<4.0.0)
Requires-Dist: litellm (>=1.73.6,<2.0.0)
Requires-Dist: loguru (>=0.7.3,<0.8.0)
Requires-Dist: pathspec (>=0.12.1,<0.13.0)
Requires-Dist: pydantic (>=2.10.4,<3.0.0)
Requires-Dist: rich (>=14.0.0,<15.0.0)
Requires-Dist: typing-extensions (>=4.12.2,<5.0.0)
